{
    "title": "屠宰稅法",
    "versions": [
        "中華民國76年4月14日廢止",
        "中華民國76年4月24日公布"
    ],
    "types": [
        "廢止理由",
        "立法歷程"
    ],
    "law_data": [
        {
            "note": "(徵收屠宰稅依據)",
            "rule_no": "第一條",
            "content": "　　各縣（市）（局）徵收屠宰稅依本法之規定。",
            "relates": {}
        },
        {
            "note": "(用辭定義)",
            "rule_no": "第二條",
            "content": "　　本法用辭之定義如左：\n　　一、屠宰牲畜：指豬、牛、羊三種為限。\n　　二、屠商：指營販牲畜肉類之人。\n　　三、屠宰人：指以屠宰牲畜為業或自宰自用之人。\n　　四、納稅義務人：指報宰牲畜之人。\n　　五、私宰：指未經報稅，或未經報准在指定之公共屠宰場所以外地方自行屠宰。",
            "relates": {}
        },
        {
            "note": "(屠宰稅之徵收)",
            "rule_no": "第三條",
            "content": "　　凡屠宰牲畜，除經檢查不能食用者外，無論自用或出售，均應徵收屠宰稅，但不得以任何名目增收附加稅捐。",
            "relates": {}
        },
        {
            "note": "(屠商及以屠宰為業之人之登記領照)",
            "rule_no": "第四條",
            "content": "　　凡營販牲畜肉類之屠商及以屠宰為業之人，執業前均應向當地主管稽徵機關登記領照。",
            "relates": {}
        },
        {
            "note": "(屠宰稅率)",
            "rule_no": "第五條",
            "content": "　　屠宰稅從價徵收，其稅率最高不得超過百分之十二。",
            "relates": {}
        },
        {
            "note": "(牲畜價格之計算)",
            "rule_no": "第六條",
            "content": "　　牲畜價格，依標準重量，按每公斤單價計算，其標準重量及單價由省（市）政府定期派員調查，並依據調查實際情形，統一規定，公布課徵。",
            "relates": {}
        },
        {
            "note": "(徵收率之擬定)",
            "rule_no": "第七條",
            "content": "　　屠宰稅之徵收率，由各縣（市）（局）政府擬定，提經當地民意機關通過，層轉財政部備案。但在動員戡亂時期，得由省政府統一規定，仍送財政部備案。",
            "relates": {}
        },
        {
            "note": "(屠宰稅徵收之限制規定)",
            "rule_no": "第八條",
            "content": "　　屠宰稅由主管稽徵機關直接經徵，不得招商包徵，或委託其他機關代徵。",
            "relates": {}
        },
        {
            "note": "(公共屠宰場)",
            "rule_no": "第九條",
            "content": "　　各縣（市）（局）政府視轄區屠宰量之多寡，得設立公共屠宰場，由當地主管稽徵機關直接管理。經省（市）政府核定酌收使用費，最高不得超過完稅價格百分之一。\n　　前項屠宰場使用費，劃分為管理費與修建費，其比例由省（市）政府統籌規定，管理費列入主管稽徵機關預算，作為管理支出之用，修建費列入縣（市）（局）預算，作為擴建設備之用，均不得移作他用。",
            "relates": {}
        },
        {
            "note": "(屠宰之檢驗)",
            "rule_no": "第十條",
            "content": "　　凡屠宰之牲畜，應在指定之公共屠宰場，或報准指定地方檢驗屠宰。",
            "relates": {}
        },
        {
            "note": "(罰鍰)",
            "rule_no": "第十一條",
            "content": "　　屠宰稅納稅義務人，如有隱匿私宰逃漏牲畜稅款情事，除追繳應納稅款外，並按其應納稅額處以十倍之罰鍰。",
            "relates": {}
        },
        {
            "note": "(私宰處罰)",
            "rule_no": "第十二條",
            "content": "　　凡飲食業及肉類製造業持有屠宰肉類，如經查獲仍不指出肉類來源或私宰人姓名時，依本法第十一條之規定以私宰處罰。",
            "relates": {}
        },
        {
            "note": "(現金保證)",
            "rule_no": "第十三條",
            "content": "　　查獲之私宰案件，在移送法院裁定前，應由私宰人取具殷實舖保或繳納應納稅額及罰鍰等同額之現金保證，或將查獲之私宰肉類先行拍賣，存備抵繳本稅及罰鍰。",
            "relates": {}
        },
        {
            "note": "(及時拍賣程序)",
            "rule_no": "第十四條",
            "content": "　　查獲無主私宰牲畜鮮肉，應即時拍賣，並公告揭示，如無人認領時，其所得價款扣除應納稅款後解繳公庫。",
            "relates": {}
        },
        {
            "note": "(罰鍰裁定之繳納及強制執行)",
            "rule_no": "第十五條",
            "content": "　　本法之罰鍰，由主管稽徵機關移送法院裁定，限期令受罰人繳納。\n　　前項罰鍰及主管稽徵機關核定補繳之應納稅額，逾期不繳者，併由法院依法強制執行。\n　　第一項罰鍰案件，主管稽徵機關於移送法院裁定前，應以書面通知受處分人。",
            "relates": {}
        },
        {
            "note": "(裁定程序)",
            "rule_no": "第十六條",
            "content": "　　前條裁定，法院應於收受主管稽徵機關移送文書之日起七日內為之，主管稽徵機關或受處分人不服法院裁定時，得於接到法院通知書十日內提出抗告，但不得再抗告。",
            "relates": {}
        },
        {
            "note": "(屠宰稅徵收細則)",
            "rule_no": "第十七條",
            "content": "　　屠宰稅徵收細則，由各省（市）政府依本法分別擬訂，送財政部備案。",
            "relates": {}
        },
        {
            "note": "(施行日)",
            "rule_no": "第十八條",
            "content": "　　本法自公布日施行。",
            "relates": {}
        }
    ],
    "deprecated_reason": "　　因屠宰稅逃漏嚴重，又難以全面查緝，稽徵成本亦高，而屠體驗印，有礙國內製革工業之發展。且屠體未經檢查，影響國民健康，因此政府訂定多項行政法規，以玆管理，故將已不符需要之屠宰稅法加以廢止。",
    "law_history": [
        {
            "進度": "一讀",
            "會議日期": "760109",
            "立法紀錄": "76卷3期2010號 2-2頁",
            "立法紀錄連結": "http://lis.ly.gov.tw/ttscgi/lgimg?@xdd!cecacbc7cccbcfcdcacc81c8c9cfcfcccfcfc4cfcfcfcdc4cfcfcfcd",
            "關係文書": [
                [
                    "提案",
                    "http://lis.ly.gov.tw/lgcgi/lgmeetimage?cfcec8c7cfc6cfcfc5cdcbcdd2cdcbca"
                ]
            ]
        },
        {
            "進度": "委員會審查",
            "會議日期": "760314",
            "立法紀錄": "76卷39期2046號 151-160頁",
            "立法紀錄連結": "http://lis.ly.gov.tw/ttscgi/lgimg?@xdd!cecacbc7cccbcfcdcacc81c8c9cfccc6cfcfc4cfcecacec4cfcec9cf",
            "關係文書": []
        },
        {
            "進度": "二讀(廣泛討論)",
            "會議日期": "760414",
            "立法紀錄": "76卷30期2037號 12-16頁",
            "立法紀錄連結": "http://lis.ly.gov.tw/ttscgi/lgimg?@xdd!cecacbc7cccbcfcdcacc81c8c9cfcccfcfcfc4cfcfcecdc4cfcfcec9",
            "關係文書": []
        },
        {
            "進度": "三讀",
            "會議日期": "760414",
            "立法紀錄": "76卷30期2037號 12-16頁",
            "立法紀錄連結": "http://lis.ly.gov.tw/ttscgi/lgimg?@xdd!cecacbc7cccbcfcdcacc81c8c9cfcccfcfcfc4cfcfcecdc4cfcfcec9",
            "關係文書": []
        }
    ]
}